signed_generator/__init__.py
signed_generator/attribute.py
signed_generator/constants.py
signed_generator/credential_proof_handler.py
signed_generator/issue_certificate_gen.py
signed_generator/merkle_proof_gen.py
signed_generator/schema.py
signed_generator/setup.py
signed_generator/sign_vc.py
signed_generator/signed_gen.py
signed_generator/utils.py
signedgen-1.0.0.dist-info/licenses/LICENSE
signedgen-1.0.0.dist-info/METADATA
signedgen-1.0.0.dist-info/WHEEL
signedgen-1.0.0.dist-info/top_level.txt
signedgen-1.0.0.dist-info/RECORD
