Metadata-Version: 2.4
Name: signedGen
Version: 1.0.0
Summary: A package for generating signed certificates with issuer and subject information.
Author: EveryCRED
Author-email: EveryCRED <admin@everycred.com>
Project-URL: Homepage, https://github.com/pypa/sampleproject
Project-URL: Issues, https://github.com/pypa/sampleproject/issues
Classifier: Programming Language :: Python :: 3
Classifier: License :: OSI Approved :: MIT License
Classifier: Operating System :: OS Independent
Requires-Python: >=3.8
License-File: LICENSE
Dynamic: author
Dynamic: license-file
Dynamic: requires-python
